{
  "match_id": 8366448601,
  "duration": 2005,
  "players": [
    {
      "account_id": 171262902,
      "kills": 8,
      "deaths": 5,
      "last_hits": 252,
      "denies": 14,
      "gold_per_min": 533,
      "tower_kills": 1,
      "obs_placed": 0,
      "camps_stacked": 0,
      "rune_pickups": 3,
      "roshan_kills": 0,
      "teamfight_participation": 0.6666667,
      "stuns": 0,
      "courier_kills": 0,
      "firstblood_claimed": 0,
      "smoke_uses": 0
    },
    {
      "account_id": 93817671,
      "kills": 4,
      "deaths": 14,
      "last_hits": 50,
      "denies": 2,
      "gold_per_min": 279,
      "tower_kills": 0,
      "obs_placed": 11,
      "camps_stacked": 2,
      "rune_pickups": 0,
      "roshan_kills": 0,
      "teamfight_participation": 0.625,
      "stuns": 0,
      "courier_kills": 0,
      "firstblood_claimed": 1,
      "smoke_uses": 2
    },
    {
      "account_id": 97590558,
      "kills": 1,
      "deaths": 11,
      "last_hits": 242,
      "denies": 6,
      "gold_per_min": 462,
      "tower_kills": 1,
      "obs_placed": 0,
      "camps_stacked": 1,
      "rune_pickups": 0,
      "roshan_kills": 0,
      "teamfight_participation": 0.625,
      "stuns": 24.766724,
      "courier_kills": 0,
      "firstblood_claimed": 0,
      "smoke_uses": 0
    },
    {
      "account_id": 16497807,
      "kills": 5,
      "deaths": 6,
      "last_hits": 50,
      "denies": 5,
      "gold_per_min": 280,
      "tower_kills": 0,
      "obs_placed": 3,
      "camps_stacked": 2,
      "rune_pickups": 0,
      "roshan_kills": 0,
      "teamfight_participation": 0.7916667,
      "stuns": 301.6339,
      "courier_kills": 0,
      "firstblood_claimed": 0,
      "smoke_uses": 2
    },
    {
      "account_id": 221666230,
      "kills": 5,
      "deaths": 9,
      "last_hits": 201,
      "denies": 23,
      "gold_per_min": 416,
      "tower_kills": 0,
      "obs_placed": 1,
      "camps_stacked": 0,
      "rune_pickups": 9,
      "roshan_kills": 0,
      "teamfight_participation": 0.41666666,
      "stuns": 0,
      "courier_kills": 0,
      "firstblood_claimed": 0,
      "smoke_uses": 0
    },
    {
      "account_id": 331855530,
      "kills": 19,
      "deaths": 2,
      "last_hits": 391,
      "denies": 13,
      "gold_per_min": 959,
      "tower_kills": 5,
      "obs_placed": 0,
      "camps_stacked": 3,
      "rune_pickups": 1,
      "roshan_kills": 2,
      "teamfight_participation": 0.8181818,
      "stuns": 0,
      "courier_kills": 0,
      "firstblood_claimed": 0,
      "smoke_uses": 0
    },
    {
      "account_id": 480412663,
      "kills": 8,
      "deaths": 2,
      "last_hits": 259,
      "denies": 11,
      "gold_per_min": 606,
      "tower_kills": 0,
      "obs_placed": 2,
      "camps_stacked": 1,
      "rune_pickups": 11,
      "roshan_kills": 0,
      "teamfight_participation": 0.6818182,
      "stuns": 43.03279,
      "courier_kills": 0,
      "firstblood_claimed": 0,
      "smoke_uses": 0
    },
    {
      "account_id": 165564598,
      "kills": 7,
      "deaths": 5,
      "last_hits": 175,
      "denies": 4,
      "gold_per_min": 524,
      "tower_kills": 1,
      "obs_placed": 0,
      "camps_stacked": 1,
      "rune_pickups": 1,
      "roshan_kills": 0,
      "teamfight_participation": 0.52272725,
      "stuns": 26.732344,
      "courier_kills": 0,
      "firstblood_claimed": 0,
      "smoke_uses": 0
    },
    {
      "account_id": 317880638,
      "kills": 4,
      "deaths": 7,
      "last_hits": 61,
      "denies": 1,
      "gold_per_min": 381,
      "tower_kills": 0,
      "obs_placed": 7,
      "camps_stacked": 1,
      "rune_pickups": 2,
      "roshan_kills": 0,
      "teamfight_participation": 0.6363636,
      "stuns": 44.667194,
      "courier_kills": 0,
      "firstblood_claimed": 0,
      "smoke_uses": 3
    },
    {
      "account_id": 196878136,
      "kills": 6,
      "deaths": 8,
      "last_hits": 34,
      "denies": 0,
      "gold_per_min": 377,
      "tower_kills": 0,
      "obs_placed": 6,
      "camps_stacked": 2,
      "rune_pickups": 8,
      "roshan_kills": 0,
      "teamfight_participation": 0.65909094,
      "stuns": 45.500656,
      "courier_kills": 0,
      "firstblood_claimed": 0,
      "smoke_uses": 2
    }
  ]
}