{
  "match_id": 8366548746,
  "duration": 2729,
  "players": [
    {
      "account_id": 96183976,
      "kills": 8,
      "deaths": 5,
      "last_hits": 529,
      "denies": 13,
      "gold_per_min": 674,
      "tower_kills": 1,
      "obs_placed": 0,
      "camps_stacked": 4,
      "rune_pickups": 4,
      "roshan_kills": 1,
      "teamfight_participation": 0.6363636,
      "stuns": 19.233973,
      "courier_kills": 0,
      "firstblood_claimed": 0,
      "smoke_uses": 0
    },
    {
      "account_id": 312436974,
      "kills": 6,
      "deaths": 6,
      "last_hits": 297,
      "denies": 8,
      "gold_per_min": 466,
      "tower_kills": 1,
      "obs_placed": 2,
      "camps_stacked": 2,
      "rune_pickups": 8,
      "roshan_kills": 0,
      "teamfight_participation": 0.59090906,
      "stuns": 38.76585,
      "courier_kills": 0,
      "firstblood_claimed": 0,
      "smoke_uses": 0
    },
    {
      "account_id": 195108598,
      "kills": 5,
      "deaths": 8,
      "last_hits": 285,
      "denies": 11,
      "gold_per_min": 452,
      "tower_kills": 0,
      "obs_placed": 0,
      "camps_stacked": 1,
      "rune_pickups": 2,
      "roshan_kills": 0,
      "teamfight_participation": 0.77272725,
      "stuns": 1.5490924,
      "courier_kills": 0,
      "firstblood_claimed": 0,
      "smoke_uses": 0
    },
    {
      "account_id": 417235485,
      "kills": 1,
      "deaths": 7,
      "last_hits": 136,
      "denies": 0,
      "gold_per_min": 308,
      "tower_kills": 0,
      "obs_placed": 7,
      "camps_stacked": 5,
      "rune_pickups": 4,
      "roshan_kills": 0,
      "teamfight_participation": 0.45454547,
      "stuns": 34.33367,
      "courier_kills": 2,
      "firstblood_claimed": 0,
      "smoke_uses": 0
    },
    {
      "account_id": 134556694,
      "kills": 1,
      "deaths": 12,
      "last_hits": 15,
      "denies": 3,
      "gold_per_min": 254,
      "tower_kills": 0,
      "obs_placed": 12,
      "camps_stacked": 0,
      "rune_pickups": 3,
      "roshan_kills": 0,
      "teamfight_participation": 0.54545456,
      "stuns": 87.8335,
      "courier_kills": 0,
      "firstblood_claimed": 0,
      "smoke_uses": 8
    },
    {
      "account_id": 124801257,
      "kills": 7,
      "deaths": 2,
      "last_hits": 575,
      "denies": 20,
      "gold_per_min": 860,
      "tower_kills": 8,
      "obs_placed": 0,
      "camps_stacked": 3,
      "rune_pickups": 4,
      "roshan_kills": 1,
      "teamfight_participation": 0.65789473,
      "stuns": 68.700294,
      "courier_kills": 1,
      "firstblood_claimed": 0,
      "smoke_uses": 0
    },
    {
      "account_id": 858106446,
      "kills": 23,
      "deaths": 3,
      "last_hits": 482,
      "denies": 11,
      "gold_per_min": 833,
      "tower_kills": 1,
      "obs_placed": 2,
      "camps_stacked": 2,
      "rune_pickups": 14,
      "roshan_kills": 1,
      "teamfight_participation": 0.81578946,
      "stuns": 9.838063,
      "courier_kills": 0,
      "firstblood_claimed": 0,
      "smoke_uses": 0
    },
    {
      "account_id": 431770905,
      "kills": 2,
      "deaths": 3,
      "last_hits": 296,
      "denies": 6,
      "gold_per_min": 575,
      "tower_kills": 0,
      "obs_placed": 0,
      "camps_stacked": 0,
      "rune_pickups": 2,
      "roshan_kills": 0,
      "teamfight_participation": 0.7894737,
      "stuns": 49.200645,
      "courier_kills": 0,
      "firstblood_claimed": 0,
      "smoke_uses": 0
    },
    {
      "account_id": 256156323,
      "kills": 2,
      "deaths": 6,
      "last_hits": 49,
      "denies": 4,
      "gold_per_min": 352,
      "tower_kills": 0,
      "obs_placed": 10,
      "camps_stacked": 3,
      "rune_pickups": 4,
      "roshan_kills": 0,
      "teamfight_participation": 0.7105263,
      "stuns": 113.09991,
      "courier_kills": 2,
      "firstblood_claimed": 0,
      "smoke_uses": 3
    },
    {
      "account_id": 108958769,
      "kills": 4,
      "deaths": 8,
      "last_hits": 47,
      "denies": 2,
      "gold_per_min": 352,
      "tower_kills": 0,
      "obs_placed": 9,
      "camps_stacked": 4,
      "rune_pickups": 3,
      "roshan_kills": 0,
      "teamfight_participation": 0.55263156,
      "stuns": 8.000245,
      "courier_kills": 0,
      "firstblood_claimed": 1,
      "smoke_uses": 4
    }
  ]
}