{
  "match_id": 8390064013,
  "duration": 1753,
  "players": [
    {
      "account_id": 91730177,
      "kills": 2,
      "deaths": 4,
      "last_hits": 36,
      "denies": 6,
      "gold_per_min": 298,
      "tower_kills": 0,
      "obs_placed": 9,
      "camps_stacked": 6,
      "rune_pickups": 2,
      "roshan_kills": 0,
      "teamfight_participation": 0.6551724,
      "stuns": 63.099728,
      "courier_kills": 0,
      "firstblood_claimed": 0,
      "smoke_uses": 2
    },
    {
      "account_id": 190826739,
      "kills": 6,
      "deaths": 3,
      "last_hits": 199,
      "denies": 11,
      "gold_per_min": 548,
      "tower_kills": 0,
      "obs_placed": 0,
      "camps_stacked": 2,
      "rune_pickups": 2,
      "roshan_kills": 0,
      "teamfight_participation": 0.55172414,
      "stuns": 48.566624,
      "courier_kills": 0,
      "firstblood_claimed": 0,
      "smoke_uses": 0
    },
    {
      "account_id": 58513047,
      "kills": 7,
      "deaths": 1,
      "last_hits": 212,
      "denies": 5,
      "gold_per_min": 604,
      "tower_kills": 2,
      "obs_placed": 1,
      "camps_stacked": 1,
      "rune_pickups": 8,
      "roshan_kills": 0,
      "teamfight_participation": 0.79310346,
      "stuns": 0,
      "courier_kills": 0,
      "firstblood_claimed": 0,
      "smoke_uses": 0
    },
    {
      "account_id": 105045291,
      "kills": 5,
      "deaths": 2,
      "last_hits": 36,
      "denies": 5,
      "gold_per_min": 351,
      "tower_kills": 0,
      "obs_placed": 4,
      "camps_stacked": 6,
      "rune_pickups": 3,
      "roshan_kills": 0,
      "teamfight_participation": 0.6551724,
      "stuns": 108.43304,
      "courier_kills": 0,
      "firstblood_claimed": 1,
      "smoke_uses": 2
    },
    {
      "account_id": 458287006,
      "kills": 9,
      "deaths": 1,
      "last_hits": 316,
      "denies": 27,
      "gold_per_min": 755,
      "tower_kills": 4,
      "obs_placed": 0,
      "camps_stacked": 3,
      "rune_pickups": 0,
      "roshan_kills": 1,
      "teamfight_participation": 0.6896552,
      "stuns": 4.666694,
      "courier_kills": 0,
      "firstblood_claimed": 0,
      "smoke_uses": 0
    },
    {
      "account_id": 81475303,
      "kills": 4,
      "deaths": 7,
      "last_hits": 211,
      "denies": 13,
      "gold_per_min": 493,
      "tower_kills": 1,
      "obs_placed": 0,
      "camps_stacked": 2,
      "rune_pickups": 1,
      "roshan_kills": 0,
      "teamfight_participation": 0.6363636,
      "stuns": 0,
      "courier_kills": 0,
      "firstblood_claimed": 0,
      "smoke_uses": 0
    },
    {
      "account_id": 94439767,
      "kills": 2,
      "deaths": 3,
      "last_hits": 177,
      "denies": 5,
      "gold_per_min": 446,
      "tower_kills": 0,
      "obs_placed": 0,
      "camps_stacked": 4,
      "rune_pickups": 0,
      "roshan_kills": 0,
      "teamfight_participation": 0.72727275,
      "stuns": 10.865626,
      "courier_kills": 0,
      "firstblood_claimed": 0,
      "smoke_uses": 0
    },
    {
      "account_id": 90423751,
      "kills": 2,
      "deaths": 8,
      "last_hits": 19,
      "denies": 1,
      "gold_per_min": 240,
      "tower_kills": 0,
      "obs_placed": 8,
      "camps_stacked": 5,
      "rune_pickups": 5,
      "roshan_kills": 0,
      "teamfight_participation": 0.72727275,
      "stuns": 17.466724,
      "courier_kills": 2,
      "firstblood_claimed": 0,
      "smoke_uses": 3
    },
    {
      "account_id": 191362875,
      "kills": 0,
      "deaths": 6,
      "last_hits": 117,
      "denies": 4,
      "gold_per_min": 326,
      "tower_kills": 1,
      "obs_placed": 3,
      "camps_stacked": 6,
      "rune_pickups": 1,
      "roshan_kills": 0,
      "teamfight_participation": 0.36363637,
      "stuns": 4.8001223,
      "courier_kills": 2,
      "firstblood_claimed": 0,
      "smoke_uses": 1
    },
    {
      "account_id": 154974246,
      "kills": 3,
      "deaths": 5,
      "last_hits": 205,
      "denies": 5,
      "gold_per_min": 508,
      "tower_kills": 0,
      "obs_placed": 3,
      "camps_stacked": 0,
      "rune_pickups": 9,
      "roshan_kills": 0,
      "teamfight_participation": 0.8181818,
      "stuns": 82.36545,
      "courier_kills": 0,
      "firstblood_claimed": 0,
      "smoke_uses": 0
    }
  ]
}