{
  "player_id": "100058342",
  "nickname": "skiter",
  "team": "Team Falcons",
  "matches_analyzed": 16,
  "tournament_id": 18324,
  "stats": {
    "kills": 9.06,
    "deaths": 4.5,
    "assists": 12.44,
    "last_hits": 604.75,
    "denies": 11.81,
    "gold_per_min": 741.31,
    "xp_per_min": 898,
    "tower_kills": 3.62,
    "observer_uses": 0.25,
    "camps_stacked": 3.62,
    "rune_pickups": 5.06,
    "roshan_kills": 0.88,
    "teamfight_participation": 0.68,
    "stuns": 15.69,
    "courier_kills": 0.31,
    "smoke_uses": 0.12,
    "first_bloods": 0.25,
    "hero_damage": 34526.81,
    "hero_healing": 591.94,
    "tower_damage": 13152.44
  },
  "last_updated": "2025-09-08T03:24:17.189391",
  "position": 1
}